airgapper/__init__.py
airgapper/__main__.py
airgapper/dataclasses.py
airgapper/enum.py
airgapper/exceptions.py
airgapper/utils.py
airgapper/version.py
airgapper/modules/__init__.py
airgapper/modules/bitnami_helm.py
airgapper/modules/docker.py
airgapper/modules/maven_helper.py
airgapper/modules/pypi.py
airgapper/repositories/__init__.py
airgapper/repositories/harbor.py
airgapper/repositories/nexus.py
airgapper-0.2.0.dist-info/licenses/LICENSE
airgapper-0.2.0.dist-info/METADATA
airgapper-0.2.0.dist-info/WHEEL
airgapper-0.2.0.dist-info/entry_points.txt
airgapper-0.2.0.dist-info/top_level.txt
airgapper-0.2.0.dist-info/RECORD
