Metadata-Version: 2.4
Name: airgapper
Version: 0.2.0
Summary: Helper to download packages/images for airgapped applications.
Author: Puggrammer
Project-URL: Homepage, https://github.com/puggrammer/airgapper
Keywords: offline,air gap,airgap,airgapped
Classifier: Programming Language :: Python :: 3
Classifier: License :: OSI Approved :: MIT License
Classifier: Operating System :: OS Independent
Classifier: Intended Audience :: Developers
Classifier: Development Status :: 4 - Beta
Requires-Python: >=3.7
License-File: LICENSE
Requires-Dist: requests
Dynamic: license-file
